evspy/__init__.py
evspy/visualisations.py
evspy/multi_stage_model/__init__.py
evspy/multi_stage_model/consolidation.py
evspy/multi_stage_model/decoupled_fdm.py
evspy/multi_stage_model/distorted_isotaches.py
evspy/multi_stage_model/viscous_swelling.py
evspy/single_stage_model/__init__.py
evspy/single_stage_model/creep_swelling_model.py
evspy/single_stage_model/model_run.py
evspy/utils/__init__.py
evspy/utils/helper_functions.py
evspy/utils/loading_empirical_data.py
evspy/utils/loadsteps.py
tests/__init__.py
tests/test_helper_functions.py
tests/test_multistage.py
tests/test_singlestage.py
evspy-0.2.1.dist-info/LICENSE
evspy-0.2.1.dist-info/METADATA
evspy-0.2.1.dist-info/WHEEL
evspy-0.2.1.dist-info/top_level.txt
evspy-0.2.1.dist-info/RECORD
