Metadata-Version: 2.1
Name: evspy
Version: 0.2.1
Summary: Modelling of creep and swelling during unloading
Home-page: http://github.com/thomasvergote/evspy
Author: Thomas Vergote
Author-email: thomas@inferensics.be
License: GPL v3
Keywords: engineering,geotechnical
Platform: UNKNOWN
Classifier: Programming Language :: Python :: 3
Classifier: Operating System :: OS Independent
License-File: LICENSE
